LICENSE.txt
MANIFEST.in
README.md
setup.cfg
setup.py
bin/methylpy
docs/README.rst
methylpy/DMRfind.py
methylpy/__init__.py
methylpy/call_mc_pe.py
methylpy/call_mc_se.py
methylpy/parser.py
methylpy/rms.cpp
methylpy/run_rms_tests.out
methylpy/utilities.py
methylpy.egg-info/PKG-INFO
methylpy.egg-info/SOURCES.txt
methylpy.egg-info/dependency_links.txt
methylpy.egg-info/requires.txt
methylpy.egg-info/top_level.txt
test/test.py