Metadata-Version: 1.0
Name: methylpy
Version: 1.3.7
Summary: Bisulfite sequencing data processing and differential methylation analysis
Home-page: UNKNOWN
Author: Yupeng He
Author-email: yupeng.he.bioinfo@gmail.com
License: LICENSE.txt
Keywords: Bioinformatics pipeline,DNA methylation,Bisulfite sequencing data,Nome-seq data,Differential methylation,Calling DMRs,Epigenetics,Functional genomics
Platform: UNKNOWN
